MANIFEST.in
README
setup.py
src/hgextensions/__init__.py
src/hgextensions/commitsigs/__init__.py
src/hgextensions/commitsigs/commitsigs.py
src/hgextensions/commitsigs/hgredsdenyhook.py
src/redsmaster/__init__.py
src/redsmaster/accesscontrol.py
src/redsmaster/app.py
src/redsmaster/authfilestore.py
src/redsmaster/command.py
src/redsmaster/config.py
src/redsmaster/daemonize.py
src/redsmaster/efs.py
src/redsmaster/exc.py
src/redsmaster/log.py
src/redsmaster/model.py
src/redsmaster/server.py
src/redsmaster/status.py
src/redsmaster/util.py
src/redsmaster/versioncontrol.py
src/redsmaster.egg-info/PKG-INFO
src/redsmaster.egg-info/SOURCES.txt
src/redsmaster.egg-info/dependency_links.txt
src/redsmaster.egg-info/entry_points.txt
src/redsmaster.egg-info/requires.txt
src/redsmaster.egg-info/top_level.txt
src/redsmaster/ext/__init__.py
src/redsmaster/ext/ext_authfilestore.py
src/redsmaster/ext/ext_hgvcs.py
src/redsmaster/ext/ext_s3qlefs.py
src/redsmaster/ext/ext_sshserver.py
src/redsmaster/templates/hgrc.tmpl
src/redsmaster/templates/redsmaster.conf.tmpl