Metadata-Version: 1.1
Name: redsmaster
Version: 1.0.2
Summary: Revision controlled document storage for cloud services
Home-page: --
Author: Tobias Pöppke
Author-email: t.poeppke@gmx.de
License: Apache
Platform: POSIX
Platform: UNIX
Platform: Linux
Provides: redsmaster
